{
      "data": [
      {
      "author": "Liam Stack and Rawan Sheikh Ahmad",
      "title": "Israeli Strikes on Northern Gaza Kill at Least 20, Aid Workers Say",
      "description": "Israel’s military said it was “operating with great force” against Hamas and allied groups and issued new evacuation orders, as it also continued its campaign in Lebanon.",
      "url": "https://www.nytimes.com/2024/10/12/world/middleeast/israel-gaza-lebanon-attacks.html",
      "source": "The New York Times",
      "image": "https://static01.nyt.com/images/2024/10/12/multimedia/12mideast-ledeall-vgwz/12mideast-ledeall-vgwz-mediumSquareAt3X.jpg",
      "category": "general",
      "language": "en",
      "country": "us",
      "published_at": "2024-10-12T10:32:30+00:00"
      },
      {
      "author": "Atlántico",
      "title": "El Coruxo se propone sumar más en casa",
      "description": "El equipo vigués recibe hoy a la Gimnástica de Torrelavega, penúltimo clasificado y que aún no conoce la victoria (17:00, O Vao)",
      "url": "https://www.atlantico.net/articulo/deporte-local/coruxo-propone-sumar-mas-casa/202410121232071054666.html",
      "source": "atlantico",
      "image": "https://www.atlantico.net/media/atlantico/images/2024/10/12/2024101212312768314.jpg",
      "category": "general",
      "language": "es",
      "country": "es",
      "published_at": "2024-10-12T10:32:07+00:00"
      },
      {
      "author": null,
      "title": "Merz warnt CDU und CSU vor Koalitionswahlkampf",
      "description": "Friedrich Merz schwört die Union auf dem CSU-Parteitag auf den Wahlkampf ein. Und gibt dafür eine klare Marschrichtung vor.",
      "url": "https://www.radioduisburg.de/artikel/merz-warnt-cdu-und-csu-vor-koalitionswahlkampf-2129722.html",
      "source": "radioduisburg",
      "image": null,
      "category": "general",
      "language": "de",
      "country": "de",
      "published_at": "2024-10-12T10:32:06+00:00"
      },
      {
      "author": null,
      "title": "CSU-Parteitag: Merz warnt CDU und CSU vor Koalitionswahlkampf",
      "description": "Friedrich Merz schwört die Union auf dem CSU-Parteitag auf den Wahlkampf ein. Und gibt dafür eine klare Marschrichtung vor.",
      "url": "https://www.stern.de/politik/deutschland/csu-parteitag--merz-warnt-cdu-und-csu-vor-koalitionswahlkampf-35138078.html?utm_campaign=tag-im-ueberblick&utm_medium=rssfeed&utm_source=standard",
      "source": "stern",
      "image": "https://image.stern.de/35138194/t/L7/v1/w1440/r1.7778/-/12--uwksafucyhv1axw800h600jpeg---a45f4c97dccf4e43.jpg",
      "category": "general",
      "language": "de",
      "country": "de",
      "published_at": "2024-10-12T10:32:06+00:00"
      },
      {
      "author": "redaktion@ad-hoc-news.de",
      "title": "Friedrich Merz schwört die Union auf dem CSU-Parteitag auf den Wahlkampf ein.",
      "description": "Friedrich Merz schwört die Union auf dem CSU-Parteitag auf den Wahlkampf ein.",
      "url": "https://www.ad-hoc-news.de/politik/friedrich-merz-schwoert-die-union-auf-dem-csu-parteitag-auf-den-wahlkampf/65918338",
      "source": "ad-hoc-news",
      "image": null,
      "category": "general",
      "language": "de",
      "country": "de",
      "published_at": "2024-10-12T10:32:06+00:00"
      },
      {
      "author": null,
      "title": "CSU-Parteitag: Merz warnt CDU und CSU vor Koalitionswahlkampf",
      "description": "Friedrich Merz schwört die Union auf dem CSU-Parteitag auf den Wahlkampf ein. Und gibt dafür eine klare Marschrichtung vor.",
      "url": "https://www.stern.de/politik/deutschland/csu-parteitag--merz-warnt-cdu-und-csu-vor-koalitionswahlkampf-35138078.html?utm_campaign=alle&utm_medium=rss-feed&utm_source=standard",
      "source": "stern",
      "image": "https://image.stern.de/35138194/t/L7/v1/w1440/r1.7778/-/12--uwksafucyhv1axw800h600jpeg---a45f4c97dccf4e43.jpg",
      "category": "general",
      "language": "de",
      "country": "de",
      "published_at": "2024-10-12T10:32:06+00:00"
      },
      {
      "author": null,
      "title": "Merz warnt CDU und CSU vor Koalitionswahlkampf",
      "description": "Friedrich Merz schwört die Union auf dem CSU-Parteitag auf den Wahlkampf ein. Und gibt dafür eine klare Marschrichtung vor.",
      "url": "https://www.radioberg.de/artikel/merz-warnt-cdu-und-csu-vor-koalitionswahlkampf-2129722.html",
      "source": "radioberg",
      "image": null,
      "category": "general",
      "language": "de",
      "country": "de",
      "published_at": "2024-10-12T10:32:06+00:00"
      },
      {
      "author": null,
      "title": "Merz warnt CDU und CSU vor Koalitionswahlkampf",
      "description": "Friedrich Merz schwört die Union auf dem CSU-Parteitag auf den Wahlkampf ein. Und gibt dafür eine klare Marschrichtung vor.",
      "url": "https://www.radiokoeln.de/artikel/merz-warnt-cdu-und-csu-vor-koalitionswahlkampf-2129722.html",
      "source": "radiokoeln",
      "image": null,
      "category": "general",
      "language": "de",
      "country": "de",
      "published_at": "2024-10-12T10:32:06+00:00"
      },
      {
      "author": "Aman Verma",
      "title": "All you need to know about the Hockey India League 2024",
      "description": "With 8 men's teams and 6 women's teams all set to showcase their hockey skills, the Hockey India League is getting back on track after seven years. See all the crucial details about this marquee hockey league.The post All you need to know about the Hockey India League 2024 appeared first on Inside Sport India.",
      "url": "https://www.insidesport.in/chak-de-india/all-you-need-to-know-about-the-hockey-india-league-2024/",
      "source": "Insidesport",
      "image": null,
      "category": "sports",
      "language": "en",
      "country": "us",
      "published_at": "2024-10-12T10:32:00+00:00"
      },
      {
      "author": null,
      "title": "This ultra portable power station can charge any device - and it's cheaper than you think",
      "description": "It also packs a cool fast-charge feature that means you're never without power.",
      "url": "https://www.zdnet.com/home-and-office/this-ultra-portable-power-station-can-charge-any-device-and-its-cheaper-than-you-think/#ftag=RSSbaffb68",
      "source": "zdnet",
      "image": null,
      "category": "general",
      "language": "en",
      "country": "us",
      "published_at": "2024-10-12T10:32:00+00:00"
      },
      {
      "author": null,
      "title": "Hamburger SPD wählt Tschentscher zum Spitzenkandidaten",
      "description": "Hamburgs SPD hat Peter Tschentscher zum Spitzenkandidaten gewählt. Der Bürgermeister tritt damit erneut bei der Bürgerschaftswahl im März an.",
      "url": "https://www.ndr.de/nachrichten/hamburg/Hamburger-SPD-waehlt-Tschentscher-zum-Spitzenkandidaten,spd2122.html",
      "source": "ndr",
      "image": null,
      "category": "general",
      "language": "de",
      "country": "de",
      "published_at": "2024-10-12T10:31:59+00:00"
      },
      {
      "author": "Lauren Ramsay",
      "title": "Dua Lipa's daring plunge top and £52,000 diamonds are a major party season mood",
      "description": "The British singer stunned in Christopher Esber SS25 and Tiffany & Co. jewels - see photos",
      "url": "https://www.hellomagazine.com/hfm/fashion-trends/723775/dua-lipa-plunge-top-and-52k-diamonds/",
      "source": "hellomagazine",
      "image": "https://images.hellomagazine.com/horizon/landscape/e17cea41aed3-nyc-escapades-1.jpg",
      "category": "general",
      "language": "en",
      "country": "us",
      "published_at": "2024-10-12T10:31:55+00:00"
      },
      {
      "author": null,
      "title": "\"Wenn einer zehn Tore kriegt\": Nagelsmann warnt seine DFB-Torhüter",
      "description": "Wer übernimmt den Posten des verletzten DFB-Torwarts Marc-Andre ter Stegen? Noch teilen sich Alexander Nübel und Oliver Baumann die Position in der deutschen Fußball-Nationalmannschaft. Das ist aber nicht in Stein gemeißelt.",
      "url": "https://www.n-tv.de/sport/fussball/Nagelsmann-warnt-seine-DFB-Torhueter-article25287129.html",
      "source": "n-tv",
      "image": "https://bilder1.n-tv.de/img/incoming/crop25287132/6398671227-cImg_4_3-w250/486856001.jpg",
      "category": "general",
      "language": "de",
      "country": "de",
      "published_at": "2024-10-12T10:31:53+00:00"
      },
      {
      "author": "Redaktionens textrobot",
      "title": "Villa i Malmö får nya ägare – prislappen: 5 020 000 kronor",
      "description": "Villa i Malmö får nya ägare – prislappen: 5 020 000 kronor",
      "url": "https://www.sydsvenskan.se/artikel/villa-i-malmo-far-nya-agare-prislappen-5-020-000-kronor/",
      "source": "Sydsvenskan",
      "image": null,
      "category": "general",
      "language": "sv",
      "country": "se",
      "published_at": "2024-10-12T10:31:50+00:00"
      },
      {
      "author": "Redaktionens textrobot",
      "title": "175 kvadratmeter stort kedjehus i Vellinge sålt",
      "description": "175 kvadratmeter stort kedjehus i Vellinge sålt",
      "url": "https://www.sydsvenskan.se/artikel/175-kvadratmeter-stort-kedjehus-i-vellinge-salt/",
      "source": "Sydsvenskan",
      "image": null,
      "category": "general",
      "language": "sv",
      "country": "se",
      "published_at": "2024-10-12T10:31:43+00:00"
      },
      {
      "author": null,
      "title": "Israël appelle les habitants du sud du Liban à ne pas y revenir",
      "description": "L'armée israélienne, en guerre contre le Hezbollah dans le sud du Liban, a enjoint samedi aux habitants de cette région à ne pas retourner chez eux, quelques heures après le tir de missiles par le mouvement libanais sur le nord d'Israël.",
      "url": "https://www.martinique.franceantilles.fr/actualite/international/israel-appelle-les-habitants-du-sud-du-liban-a-ne-pas-y-revenir-1007195.php",
      "source": "France-Antilles Martinique - INTERNATIONAL",
      "image": "https://medias.franceantilles.fr/api/v1/files/670a5006c7e75539a77be758?alt=file",
      "category": "general",
      "language": "fr",
      "country": "fr",
      "published_at": "2024-10-12T10:31:38+00:00"
      },
      {
      "author": "OÖ Volksblatt",
      "title": "Eindrucksvolles Finale beim Brucknerfest Linz",
      "description": "Das Internationale Brucknerfest Linz 2024 ging Freitagabend mit einer eindrucksvollen Aufführung von Anton Bruckners Sinfonie Nr. 8, c-Moll, Fassung 1890, durch das Bruckner Orchester Linz unter Markus Poschner zu Ende. Die Aufführung fand am Todestag des Komponisten in der Stiftsbasilika von St. Florian statt. Anlässlich seines 200. Geburtstages steht Oberösterreich heuer musikalisch ganz im Banne [&#8230;]Der Beitrag Eindrucksvolles Finale beim Brucknerfest Linz erschien zuerst auf Oberösterreichisches Volksblatt.",
      "url": "https://volksblatt.at/kultur-medien/eindrucksvolles-finale-beim-brucknerfest-linz-1590394/",
      "source": "volksblatt",
      "image": "https://volksblatt.at/wp-content/uploads/2024/10/1482555748_BLD_Online-300x131.jpg",
      "category": "general",
      "language": "de",
      "country": "at",
      "published_at": "2024-10-12T10:31:34+00:00"
      },
      {
      "author": "Vishal Bhawani",
      "title": "'Those outside are not better' — Brazil President gives bold statements to eliminate players playing in European leagues",
      "description": "Brazilian President Luiz Inácio Lula da Silva has stirred up the football world with his bold idea that could shake the Brazil national team.",
      "url": "https://www.sportingnews.com/us/soccer/news/brazil-president-statements-eliminate-players-european-leagues/34e60e827e9cdd6f71066eef",
      "source": "Sporting News",
      "image": "https://library.sportingnews.com/styles/crop_style_16_9_desktop/s3/2024-09/Brazil%20Futsal%2009232024.jpg?h=fba93510&amp;itok=1BbI19xY",
      "category": "sports",
      "language": "en",
      "country": "us",
      "published_at": "2024-10-12T10:31:33+00:00"
      },
      {
      "author": "Caretaker",
      "title": "What did Austin Eguavoen say about Victor Boniface’s performance vs Libya",
      "description": "Super Eagles head coach Austin Eguavoen has expressed disappointment with Victor Boniface’s performance in Nigeria’s narrow 1-0 win over Libya at the Godswill Akpabio Stadium. Despite Nigeria dominating possession, Boniface failed to impress, drawing criticism from Eguavoen after another underwhelming display in Osimhen’s absence. The 22-year-old striker has been in excellent form for Bayer Leverkusen, &#8230;The post What did Austin Eguavoen say about Victor Boniface&#8217;s performance vs Libya appeared first on SportsRation.",
      "url": "https://sportsration.com/what-did-austin-eguavoen-say-about-victor-bonifaces-performance-vs-libya/",
      "source": "Sportsration: Nigeria Soccer | World Sports",
      "image": null,
      "category": "sports",
      "language": "en",
      "country": "us",
      "published_at": "2024-10-12T10:31:27+00:00"
      },
      {
      "author": null,
      "title": "Neunjährige verletzt: Unfall - Hund zieht Mädchen auf Straße",
      "description": "Es passiert beim Gassigehen: Ein Hund zerrt ein Kind auf die Straße, eine Autofahrerin kann nicht mehr ausweichen.",
      "url": "https://www.stern.de/gesellschaft/regional/sachsen/neunjaehrige-verletzt--unfall---hund-zieht-maedchen-auf-strasse-35138182.html?utm_campaign=alle&utm_medium=rss-feed&utm_source=standard",
      "source": "stern",
      "image": "https://image.stern.de/35138184/t/Gf/v1/w1440/r1.7778/-/12--esy5dhbfhpv14axw800h600jpeg---1995c8c85fab4f19.jpg",
      "category": "general",
      "language": "de",
      "country": "de",
      "published_at": "2024-10-12T10:31:11+00:00"
      },
      {
      "author": null,
      "title": "Neunjährige verletzt: Unfall - Hund zieht Mädchen auf Straße",
      "description": "Es passiert beim Gassigehen: Ein Hund zerrt ein Kind auf die Straße, eine Autofahrerin kann nicht mehr ausweichen.",
      "url": "https://www.stern.de/gesellschaft/regional/sachsen/neunjaehrige-verletzt--unfall---hund-zieht-maedchen-auf-strasse-35138182.html?utm_campaign=tag-im-ueberblick&utm_medium=rssfeed&utm_source=standard",
      "source": "stern",
      "image": "https://image.stern.de/35138184/t/Gf/v1/w1440/r1.7778/-/12--esy5dhbfhpv14axw800h600jpeg---1995c8c85fab4f19.jpg",
      "category": "general",
      "language": "de",
      "country": "de",
      "published_at": "2024-10-12T10:31:11+00:00"
      },
      {
      "author": "ZEIT ONLINE: News -",
      "title": "Neunjährige verletzt: Unfall - Hund zieht Mädchen auf Straße",
      "description": "Neunjährige verletzt: Unfall - Hund zieht Mädchen auf Straße",
      "url": "https://www.zeit.de/news/2024-10/12/unfall-hund-zieht-maedchen-auf-strasse",
      "source": "ZEIT",
      "image": "https://img.zeit.de/news/2024-10/12/unfall-hund-zieht-maedchen-auf-strasse-image-group/original__640x360",
      "category": "general",
      "language": "de",
      "country": "de",
      "published_at": "2024-10-12T10:31:11+00:00"
      },
      {
      "author": null,
      "title": "Neue Einigkeit mit der Schwester: Merz löst bei CSU-Parteitag Begeisterung aus",
      "description": "Der CSU-Parteitag ist für CDU-Vorsitzende nicht immer ein Vergnügen. CDU-Chef Merz wird jedoch in Augsburg gefeiert. Er revanchiert sich mit einer Loyalitätserklärung an die Schwesterpartei.",
      "url": "https://www.n-tv.de/politik/Merz-loest-bei-CSU-Parteitag-Begeisterung-aus-article25287135.html",
      "source": "n-tv",
      "image": "https://bilder3.n-tv.de/img/incoming/crop25287154/0478676788-cImg_4_3-w250/cb3c1d36217d0385a3a5d32ea2bbc51b.jpg",
      "category": "general",
      "language": "de",
      "country": "de",
      "published_at": "2024-10-12T10:31:04+00:00"
      },
      {
      "author": "BN Staff",
      "title": "Boxing betting predictions: Beterbiev vs. Bivol Full Card",
      "description": "The post Boxing betting predictions: Beterbiev vs. Bivol Full Card appeared first on Boxing News.We look ahead at the form guide and some tips for the big fight card in Riyadh on SaturdayThe post Boxing betting predictions: Beterbiev vs. Bivol Full Card appeared first on Boxing News.",
      "url": "https://boxingnewsonline.net/boxing-betting-predictions-beterbiev-vs-bivol-full-card/",
      "source": "Boxing News",
      "image": null,
      "category": "sports",
      "language": "en",
      "country": "us",
      "published_at": "2024-10-12T10:31:04+00:00"
      }
      ]
      }